egygeo/__init__.py
egygeo/egygeo.py
egygeo-1.1.1.dist-info/LICENSE
egygeo-1.1.1.dist-info/METADATA
egygeo-1.1.1.dist-info/WHEEL
egygeo-1.1.1.dist-info/top_level.txt
egygeo-1.1.1.dist-info/RECORD
