Metadata-Version: 2.1
Name: egygeo
Version: 1.1.1
Summary: A Python package designed to provide easy access to the geographic coordinates (latitude and longitude) of various Egyptian subdivisions.
Author: Sara Habib
Author-email: sara.habib48@gmail.com
License-File: LICENSE
